<?xml version="1.0" encoding="utf-8" ?><dwsync><file name="news.php" server="ftp.lolipop.jp/domain/web_friekobo2021/" local="3713618305" remote="3722224620" Dst="-1" /><file name="htaccess.text" server="ftp.lolipop.jp/domain/web_friekobo2021/" local="3700312112" remote="3722224620" Dst="-1" /><file name="index3.html" server="ftp.lolipop.jp/domain/web_friekobo2021/" local="3697115023" remote="3722224620" Dst="-1" /><file name="index.html" server="ftp.lolipop.jp/domain/web_friekobo2021/" local="3720365440" remote="3722224620" Dst="-1" /><file name="GALLERYpage_memo" server="ftp.lolipop.jp/domain/web_friekobo2021/" local="3699356682" remote="3722224620" Dst="-1" /><file name="about.html" server="ftp.lolipop.jp/domain/web_friekobo2021/" local="3713618159" remote="3722224620" Dst="-1" /><file name="contact.html" server="ftp.lolipop.jp/domain/web_friekobo2021/" local="3721658928" remote="3722224620" Dst="-1" /><file name="db.inc.php" server="ftp.lolipop.jp/domain/web_friekobo2021/" local="3688391168" remote="3722224680" Dst="-1" /><file name="util.inc.php" server="ftp.lolipop.jp/domain/web_friekobo2021/" local="3688390966" remote="3722224680" Dst="-1" /><file name="sass_watch.command" server="ftp.lolipop.jp/domain/web_friekobo2021/" local="3708187069" remote="3722224680" Dst="-1" /><file name="memo_howto.text" server="ftp.lolipop.jp/domain/web_friekobo2021/" local="3696940918" remote="3722224740" Dst="-1" /><file name="news.html" server="ftp.lolipop.jp/domain/web_friekobo2021/" local="3689689026" remote="3722224740" Dst="-1" /><file name="gallery.html" server="ftp.lolipop.jp/domain/web_friekobo2021/" local="3713616277" remote="3722224740" Dst="-1" /><file name="php_memo.text" server="ftp.lolipop.jp/domain/web_friekobo2021/" local="3700313927" remote="3722224740" Dst="-1" /><file name="package-lock.json" server="ftp.lolipop.jp/domain/web_friekobo2021/" local="3708774400" remote="3722224740" Dst="-1" /><file name="package.json" server="ftp.lolipop.jp/domain/web_friekobo2021/" local="3708775616" remote="3722224740" Dst="-1" /><file name="news_copy2.php" server="ftp.lolipop.jp/domain/web_friekobo2021/" local="3691421578" remote="3722224740" Dst="-1" /><file name="Newspage_memo" server="ftp.lolipop.jp/domain/web_friekobo2021/" local="3697366459" remote="3722224740" Dst="-1" /><file name="howto.html" server="ftp.lolipop.jp/domain/web_friekobo2021/" local="3713615543" remote="3722224740" Dst="-1" /><file name="aboutpage_memo" server="ftp.lolipop.jp/domain/web_friekobo2021/" local="3706352529" remote="3722224740" Dst="-1" /></dwsync>